{
    "boxShadow": "{{appsmith.theme.boxShadow.appBoxShadow}}",
    "mobileBottomRow": 11,
    "widgetName": "Container7",
    "borderColor": "#E0DEDE",
    "isCanvas": true,
    "displayName": "Container",
    "iconSVG": "/static/media/icon.c47c069fe28eb6d2d27f0fffdc053074.svg",
    "searchTags": [
        "div",
        "parent",
        "group"
    ],
    "topRow": 27,
    "bottomRow": 37,
    "parentRowSpace": 10,
    "type": "CONTAINER_WIDGET",
    "hideCard": false,
    "shouldScrollContents": true,
    "mobileRightColumn": 48,
    "animateLoading": true,
    "parentColumnSpace": 4.207763671875,
    "leftColumn": 28,
    "dynamicBindingPathList": [
        {"key": "borderRadius"},
        {"key": "boxShadow"}
    ],
    "children": [{
        "mobileBottomRow": 100,
        "widgetName": "Canvas12",
        "displayName": "Canvas",
        "topRow": 0,
        "bottomRow": 100,
        "parentRowSpace": 1,
        "type": "CANVAS_WIDGET",
        "canExtend": false,
        "hideCard": true,
        "minHeight": 100,
        "mobileRightColumn": 100.986328125,
        "parentColumnSpace": 1,
        "leftColumn": 0,
        "dynamicBindingPathList": [],
        "key": "dy1gp2i0on",
        "isDeprecated": false,
        "rightColumn": 100.986328125,
        "detachFromLayout": true,
        "widgetId": "0od63owyns",
        "containerStyle": "none",
        "minWidth": 450,
        "isVisible": true,
        "version": 1,
        "parentId": "vshx4q3q65",
        "renderMode": "CANVAS",
        "isLoading": false,
        "mobileTopRow": 0,
        "responsiveBehavior": "fill",
        "mobileLeftColumn": 0,
        "flexLayers": []
    }],
    "borderWidth": "1",
    "flexVerticalAlignment": "start",
    "key": "7n62quinso",
    "backgroundColor": "#FFFFFF",
    "isDeprecated": false,
    "rightColumn": 52,
    "dynamicHeight": "AUTO_HEIGHT",
    "widgetId": "vshx4q3q65",
    "containerStyle": "card",
    "minWidth": 450,
    "isVisible": true,
    "version": 1,
    "parentId": "0",
    "renderMode": "CANVAS",
    "isLoading": false,
    "mobileTopRow": 1,
    "responsiveBehavior": "fill",
    "originalTopRow": 27,
    "borderRadius": "{{appsmith.theme.borderRadius.appBorderRadius}}",
    "mobileLeftColumn": 24,
    "maxDynamicHeight": 9000,
    "originalBottomRow": 37,
    "minDynamicHeight": 10
}